{
    "photos": {
        "page": 1,
        "pages": 25592,
        "perpage": 6,
        "total": "153552",
        "photo": [
            {
                "id": "51146531135",
                "owner": "49271313@N00",
                "secret": "182686fc09",
                "server": "65535",
                "farm": 66,
                "title": "\u5c0f\u864e, \u5c0f\u67cf, \u85af\u76ae",
                "ispublic": 1,
                "isfriend": 0,
                "isfamily": 0
            },
            {
                "id": "51145649278",
                "owner": "49271313@N00",
                "secret": "98f53a8757",
                "server": "65535",
                "farm": 66,
                "title": "\u5c0f\u864e, \u5c0f\u67cf, \u85af\u76ae",
                "ispublic": 1,
                "isfriend": 0,
                "isfamily": 0
            },
            {
                "id": "51143501584",
                "owner": "184307436@N07",
                "secret": "22002ea23c",
                "server": "65535",
                "farm": 66,
                "title": "Felix loves his Monkey Man",
                "ispublic": 1,
                "isfriend": 0,
                "isfamily": 0
            },
            {
                "id": "51140329016",
                "owner": "147640758@N05",
                "secret": "1c4daf6d2b",
                "server": "65535",
                "farm": 66,
                "title": "Fan? Lollipop?",
                "ispublic": 1,
                "isfriend": 0,
                "isfamily": 0
            },
            {
                "id": "51141431490",
                "owner": "147640758@N05",
                "secret": "a4f7c3a840",
                "server": "65535",
                "farm": 66,
                "title": "IMG_5418",
                "ispublic": 1,
                "isfriend": 0,
                "isfamily": 0
            },
            {
                "id": "51139654452",
                "owner": "147640758@N05",
                "secret": "e943402708",
                "server": "65535",
                "farm": 66,
                "title": "IMG_5417",
                "ispublic": 1,
                "isfriend": 0,
                "isfamily": 0
            }
        ]
    },
    "stat": "ok"
}